sshai/Caddyfile
sshai/__init__.py
sshai/__main__.py
sshai/agi.py
sshai/agi_sshd
sshai/cli.py
sshai/entrypoint-server.sh
sshai/entrypoint.sh
sshai/files.txt
sshai/mcp_server_files.py
sshai/openai_assistant_instructions.md
sshai/policy_engine.py
sshai/server_motd
sshai/setup.sh
sshai/util.sh
sshai-0.0.3.dist-info/METADATA
sshai-0.0.3.dist-info/WHEEL
sshai-0.0.3.dist-info/entry_points.txt
sshai-0.0.3.dist-info/licenses/LICENSE
sshai-0.0.3.dist-info/RECORD
