Metadata-Version: 2.4
Name: sshai
Version: 0.0.3
Summary: Ghost in Shell via SSH
Project-URL: Repository, https://github.com/publicdomainrelay/sshai.git
Project-URL: Issues, https://github.com/publicdomainrelay/sshai/issues
Author-email: Public Domain <publicdomainrelay@protonmail.com>
License: Unlicense
License-File: LICENSE
Requires-Python: >=3.12
Requires-Dist: aiohttp
Requires-Dist: build
Requires-Dist: cachetools
Requires-Dist: celery[redis]
Requires-Dist: fastapi
Requires-Dist: gidgethub[aiohttp]
Requires-Dist: gunicorn
Requires-Dist: httpx
Requires-Dist: keyring
Requires-Dist: keyrings-alt
Requires-Dist: libtmux
Requires-Dist: openai
Requires-Dist: pip
Requires-Dist: psutil
Requires-Dist: pydantic
Requires-Dist: pytest
Requires-Dist: pyyaml
Requires-Dist: setuptools
Requires-Dist: snoop
Requires-Dist: uvicorn
Requires-Dist: wheel
